odoo/addons/delivery_driver_stock_picking_batch/README.rst
odoo/addons/delivery_driver_stock_picking_batch/__init__.py
odoo/addons/delivery_driver_stock_picking_batch/__manifest__.py
odoo/addons/delivery_driver_stock_picking_batch/i18n/delivery_driver_stock_picking_batch.pot
odoo/addons/delivery_driver_stock_picking_batch/i18n/es.po
odoo/addons/delivery_driver_stock_picking_batch/i18n/it.po
odoo/addons/delivery_driver_stock_picking_batch/models/__init__.py
odoo/addons/delivery_driver_stock_picking_batch/models/stock_picking_batch.py
odoo/addons/delivery_driver_stock_picking_batch/readme/CONFIGURE.md
odoo/addons/delivery_driver_stock_picking_batch/readme/CONTRIBUTORS.md
odoo/addons/delivery_driver_stock_picking_batch/readme/DESCRIPTION.md
odoo/addons/delivery_driver_stock_picking_batch/readme/USAGE.md
odoo/addons/delivery_driver_stock_picking_batch/static/description/icon.png
odoo/addons/delivery_driver_stock_picking_batch/static/description/index.html
odoo/addons/delivery_driver_stock_picking_batch/tests/__init__.py
odoo/addons/delivery_driver_stock_picking_batch/tests/test_delivery_driver_stock_picking_batch.py
odoo/addons/delivery_driver_stock_picking_batch/views/stock_picking_batch.xml
odoo_addon_delivery_driver_stock_picking_batch-18.0.1.0.1.dist-info/METADATA
odoo_addon_delivery_driver_stock_picking_batch-18.0.1.0.1.dist-info/WHEEL
odoo_addon_delivery_driver_stock_picking_batch-18.0.1.0.1.dist-info/top_level.txt
odoo_addon_delivery_driver_stock_picking_batch-18.0.1.0.1.dist-info/RECORD
