Metadata-Version: 2.1
Name: odoo-addon-delivery_driver_stock_picking_batch
Version: 18.0.1.0.1
Requires-Python: >=3.10
Requires-Dist: odoo-addon-delivery_driver==18.0.*
Requires-Dist: odoo==18.0.*
Summary: Add drivers from delivery in stock picking batch
Home-page: https://github.com/OCA/delivery-carrier
License: LGPL-3
Author: Moduon, Odoo Community Association (OCA)
Author-email: support@odoo-community.org
Classifier: Programming Language :: Python
Classifier: Framework :: Odoo
Classifier: Framework :: Odoo :: 18.0
Classifier: License :: OSI Approved :: GNU Lesser General Public License v3 (LGPLv3)
Classifier: Development Status :: 3 - Alpha
